{"id": 2022020474, "season": 20222023, "gameType": 2, "limitedScoring": false, "gameDate": "2022-12-15", "venue": {"default": "FLA Live Arena"}, "venueLocation": {"default": "Sunrise"}, "startTimeUTC": "2022-12-16T00:00:00Z", "easternUTCOffset": "-05:00", "venueUTCOffset": "-05:00", "tvBroadcasts": [{"id": 316, "market": "A", "countryCode": "US", "network": "ATTSN-PT", "sequenceNumber": 214}, {"id": 353, "market": "H", "countryCode": "US", "network": "BSFL", "sequenceNumber": 413}], "gameState": "OFF", "gameScheduleState": "OK", "periodDescriptor": {"number": 3, "periodType": "REG", "maxRegulationPeriods": 3}, "regPeriods": 3, "awayTeam": {"id": 5, "commonName": {"default": "Penguins"}, "abbrev": "PIT", "score": 4, "sog": 39, "logo": "https://assets.nhle.com/logos/nhl/svg/PIT_light.svg", "darkLogo": "https://assets.nhle.com/logos/nhl/svg/PIT_dark.svg", "placeName": {"default": "Pittsburgh"}, "placeNameWithPreposition": {"default": "Pittsburgh", "fr": "de Pittsburgh"}}, "homeTeam": {"id": 13, "commonName": {"default": "Panthers"}, "abbrev": "FLA", "score": 2, "sog": 34, "logo": "https://assets.nhle.com/logos/nhl/svg/FLA_light.svg", "darkLogo": "https://assets.nhle.com/logos/nhl/svg/FLA_dark.svg", "placeName": {"default": "Florida", "fr": "Floride"}, "placeNameWithPreposition": {"default": "Florida", "fr": "de la Floride"}}, "clock": {"timeRemaining": "00:00", "secondsRemaining": 0, "running": false, "inIntermission": false}, "playerByGameStats": {"awayTeam": {"forwards": [{"playerId": 8476326, "sweaterNumber": 15, "name": {"default": "J. Archibald"}, "position": "R", "goals": 0, "assists": 0, "points": 0, "plusMinus": 0, "pim": 0, "hits": 3, "powerPlayGoals": 0, "sog": 2, "faceoffWinningPctg": 0.0, "toi": "09:40", "blockedShots": 0, "shifts": 14, "giveaways": 0, "takeaways": 1}, {"playerId": 8475810, "sweaterNumber": 17, "name": {"default": "B. Rust"}, "position": "R", "goals": 0, "assists": 1, "points": 1, "plusMinus": 1, "pim": 0, "hits": 0, "powerPlayGoals": 0, "sog": 2, "faceoffWinningPctg": 0.0, "toi": "17:52", "blockedShots": 2, "shifts": 26, "giveaways": 0, "takeaways": 1}, {"playerId": 8476934, "sweaterNumber": 23, "name": {"default": "B. McGinn"}, "position": "L", "goals": 0, "assists": 1, "points": 1, "plusMinus": 0, "pim": 0, "hits": 0, "powerPlayGoals": 0, "sog": 3, "faceoffWinningPctg": 0.0, "toi": "13:52", "blockedShots": 1, "shifts": 24, "giveaways": 0, "takeaways": 2}, {"playerId": 8480068, "sweaterNumber": 25, "name": {"default": "R. Poehling"}, "position": "C", "goals": 0, "assists": 1, "points": 1, "plusMinus": 1, "pim": 0, "hits": 2, "powerPlayGoals": 0, "sog": 2, "faceoffWinningPctg": 0.666667, "toi": "11:58", "blockedShots": 0, "shifts": 18, "giveaways": 0, "takeaways": 0}, {"playerId": 8477953, "sweaterNumber": 42, "name": {"default": "K. Kapanen"}, "position": "R", "goals": 0, "assists": 0, "points": 0, "plusMinus": -1, "pim": 0, "hits": 0, "powerPlayGoals": 0, "sog": 2, "faceoffWinningPctg": 0.0, "toi": "08:41", "blockedShots": 0, "shifts": 13, "giveaways": 0, "takeaways": 1}, {"playerId": 8478046, "sweaterNumber": 43, "name": {"default": "D. Heinen"}, "position": "L", "goals": 0, "assists": 0, "points": 0, "plusMinus": 0, "pim": 2, "hits": 0, "powerPlayGoals": 0, "sog": 1, "faceoffWinningPctg": 0.0, "toi": "14:13", "blockedShots": 0, "shifts": 20, "giveaways": 1, "takeaways": 0}, {"playerId": 8476927, "sweaterNumber": 53, "name": {"default": "T. Blueger", "cs": "T. Blugers", "sk": "T. Blugers"}, "position": "C", "goals": 0, "assists": 0, "points": 0, "plusMinus": 0, "pim": 0, "hits": 0, "powerPlayGoals": 0, "sog": 2, "faceoffWinningPctg": 0.545455, "toi": "13:08", "blockedShots": 0, "shifts": 22, "giveaways": 0, "takeaways": 0}, {"playerId": 8477404, "sweaterNumber": 59, "name": {"default": "J. Guentzel"}, "position": "C", "goals": 2, "assists": 0, "points": 2, "plusMinus": 0, "pim": 0, "hits": 0, "powerPlayGoals": 1, "sog": 8, "faceoffWinningPctg": 0.0, "toi": "20:54", "blockedShots": 0, "shifts": 24, "giveaways": 0, "takeaways": 0}, {"playerId": 8476483, "sweaterNumber": 67, "name": {"default": "R. Rakell"}, "position": "R", "goals": 0, "assists": 1, "points": 1, "plusMinus": -1, "pim": 0, "hits": 1, "powerPlayGoals": 0, "sog": 4, "faceoffWinningPctg": 0.0, "toi": "18:48", "blockedShots": 0, "shifts": 23, "giveaways": 0, "takeaways": 0}, {"playerId": 8471215, "sweaterNumber": 71, "name": {"default": "E. Malkin"}, "position": "C", "goals": 1, "assists": 1, "points": 2, "plusMinus": 0, "pim": 0, "hits": 2, "powerPlayGoals": 1, "sog": 1, "faceoffWinningPctg": 0.461538, "toi": "14:42", "blockedShots": 0, "shifts": 18, "giveaways": 1, "takeaways": 0}, {"playerId": 8470604, "sweaterNumber": 77, "name": {"default": "J. Carter"}, "position": "C", "goals": 0, "assists": 0, "points": 0, "plusMinus": -1, "pim": 0, "hits": 1, "powerPlayGoals": 0, "sog": 2, "faceoffWinningPctg": 0.642857, "toi": "13:06", "blockedShots": 1, "shifts": 19, "giveaways": 0, "takeaways": 1}, {"playerId": 8471675, "sweaterNumber": 87, "name": {"default": "S. Crosby"}, "position": "C", "goals": 0, "assists": 2, "points": 2, "plusMinus": 0, "pim": 0, "hits": 0, "powerPlayGoals": 0, "sog": 5, "faceoffWinningPctg": 0.5, "toi": "19:09", "blockedShots": 0, "shifts": 23, "giveaways": 0, "takeaways": 1}], "defense": [{"playerId": 8477244, "sweaterNumber": 2, "name": {"default": "C. Ruhwedel"}, "position": "D", "goals": 0, "assists": 0, "points": 0, "plusMinus": -1, "pim": 0, "hits": 1, "powerPlayGoals": 0, "sog": 0, "faceoffWinningPctg": 0.0, "toi": "17:09", "blockedShots": 1, "shifts": 24, "giveaways": 0, "takeaways": 0}, {"playerId": 8475208, "sweaterNumber": 8, "name": {"default": "B. Dumoulin"}, "position": "D", "goals": 0, "assists": 0, "points": 0, "plusMinus": 0, "pim": 0, "hits": 0, "powerPlayGoals": 0, "sog": 0, "faceoffWinningPctg": 0.0, "toi": "19:35", "blockedShots": 1, "shifts": 25, "giveaways": 0, "takeaways": 1}, {"playerId": 8477969, "sweaterNumber": 28, "name": {"default": "M. Pettersson"}, "position": "D", "goals": 0, "assists": 0, "points": 0, "plusMinus": 1, "pim": 0, "hits": 0, "powerPlayGoals": 0, "sog": 2, "faceoffWinningPctg": 0.0, "toi": "22:58", "blockedShots": 0, "shifts": 28, "giveaways": 2, "takeaways": 0}, {"playerId": 8480172, "sweaterNumber": 44, "name": {"default": "J. Rutta"}, "position": "D", "goals": 0, "assists": 0, "points": 0, "plusMinus": -1, "pim": 4, "hits": 1, "powerPlayGoals": 0, "sog": 0, "faceoffWinningPctg": 0.0, "toi": "17:20", "blockedShots": 2, "shifts": 25, "giveaways": 2, "takeaways": 1}, {"playerId": 8471724, "sweaterNumber": 58, "name": {"default": "K. Letang"}, "position": "D", "goals": 1, "assists": 1, "points": 2, "plusMinus": 1, "pim": 0, "hits": 1, "powerPlayGoals": 0, "sog": 3, "faceoffWinningPctg": 0.0, "toi": "25:44", "blockedShots": 1, "shifts": 27, "giveaways": 0, "takeaways": 0}, {"playerId": 8480058, "sweaterNumber": 73, "name": {"default": "P. Joseph"}, "position": "D", "goals": 0, "assists": 0, "points": 0, "plusMinus": 0, "pim": 0, "hits": 0, "powerPlayGoals": 0, "sog": 0, "faceoffWinningPctg": 0.0, "toi": "15:14", "blockedShots": 0, "shifts": 19, "giveaways": 4, "takeaways": 0}], "goalies": [{"playerId": 8479193, "sweaterNumber": 1, "name": {"default": "C. DeSmith"}, "position": "G", "evenStrengthShotsAgainst": "0/0", "powerPlayShotsAgainst": "0/0", "shorthandedShotsAgainst": "0/0", "saveShotsAgainst": "0/0", "evenStrengthGoalsAgainst": 0, "powerPlayGoalsAgainst": 0, "shorthandedGoalsAgainst": 0, "pim": 0, "goalsAgainst": 0, "toi": "00:00", "starter": false, "shotsAgainst": 0, "saves": 0}, {"playerId": 8477465, "sweaterNumber": 35, "name": {"default": "T. Jarry"}, "position": "G", "evenStrengthShotsAgainst": "29/31", "powerPlayShotsAgainst": "3/3", "shorthandedShotsAgainst": "0/0", "saveShotsAgainst": "32/34", "savePctg": 0.941176, "evenStrengthGoalsAgainst": 2, "powerPlayGoalsAgainst": 0, "shorthandedGoalsAgainst": 0, "pim": 0, "goalsAgainst": 2, "toi": "59:57", "starter": true, "decision": "W", "shotsAgainst": 34, "saves": 32}]}, "homeTeam": {"forwards": [{"playerId": 8477935, "sweaterNumber": 9, "name": {"default": "S. Bennett"}, "position": "C", "goals": 0, "assists": 0, "points": 0, "plusMinus": -1, "pim": 0, "hits": 2, "powerPlayGoals": 0, "sog": 5, "faceoffWinningPctg": 0.434783, "toi": "19:32", "blockedShots": 0, "shifts": 23, "giveaways": 0, "takeaways": 0}, {"playerId": 8470595, "sweaterNumber": 12, "name": {"default": "E. Staal"}, "position": "C", "goals": 0, "assists": 1, "points": 1, "plusMinus": -1, "pim": 2, "hits": 0, "powerPlayGoals": 0, "sog": 4, "faceoffWinningPctg": 0.277778, "toi": "20:15", "blockedShots": 0, "shifts": 25, "giveaways": 0, "takeaways": 0}, {"playerId": 8477933, "sweaterNumber": 13, "name": {"default": "S. Reinhart"}, "position": "C", "goals": 1, "assists": 0, "points": 1, "plusMinus": -1, "pim": 0, "hits": 0, "powerPlayGoals": 0, "sog": 2, "faceoffWinningPctg": 0.0, "toi": "21:22", "blockedShots": 0, "shifts": 25, "giveaways": 2, "takeaways": 1}, {"playerId": 8480844, "sweaterNumber": 14, "name": {"default": "G. Denisenko"}, "position": "L", "goals": 0, "assists": 0, "points": 0, "plusMinus": 0, "pim": 0, "hits": 2, "powerPlayGoals": 0, "sog": 2, "faceoffWinningPctg": 0.0, "toi": "10:20", "blockedShots": 0, "shifts": 11, "giveaways": 0, "takeaways": 0}, {"playerId": 8477493, "sweaterNumber": 16, "name": {"default": "A. Barkov"}, "position": "C", "goals": 0, "assists": 0, "points": 0, "plusMinus": 0, "pim": 0, "hits": 0, "powerPlayGoals": 0, "sog": 1, "faceoffWinningPctg": 0.62963, "toi": "22:32", "blockedShots": 0, "shifts": 28, "giveaways": 2, "takeaways": 0}, {"playerId": 8480037, "sweaterNumber": 20, "name": {"default": "A. Heponiemi"}, "position": "C", "goals": 0, "assists": 0, "points": 0, "plusMinus": 0, "pim": 0, "hits": 0, "powerPlayGoals": 0, "sog": 1, "faceoffWinningPctg": 0.0, "toi": "08:13", "blockedShots": 0, "shifts": 9, "giveaways": 0, "takeaways": 0}, {"playerId": 8476393, "sweaterNumber": 21, "name": {"default": "N. Cousins"}, "position": "C", "goals": 0, "assists": 0, "points": 0, "plusMinus": 1, "pim": 0, "hits": 0, "powerPlayGoals": 0, "sog": 3, "faceoffWinningPctg": 0.0, "toi": "14:18", "blockedShots": 0, "shifts": 20, "giveaways": 0, "takeaways": 1}, {"playerId": 8474610, "sweaterNumber": 22, "name": {"default": "Z. Dalpe"}, "position": "C", "goals": 0, "assists": 0, "points": 0, "plusMinus": 0, "pim": 0, "hits": 0, "powerPlayGoals": 0, "sog": 2, "faceoffWinningPctg": 0.0, "toi": "12:35", "blockedShots": 0, "shifts": 19, "giveaways": 0, "takeaways": 0}, {"playerId": 8477409, "sweaterNumber": 23, "name": {"default": "C. Verhaeghe"}, "position": "C", "goals": 0, "assists": 1, "points": 1, "plusMinus": 0, "pim": 2, "hits": 0, "powerPlayGoals": 0, "sog": 0, "faceoffWinningPctg": 0.0, "toi": "19:12", "blockedShots": 0, "shifts": 22, "giveaways": 2, "takeaways": 0}, {"playerId": 8480185, "sweaterNumber": 27, "name": {"default": "E. Luostarinen"}, "position": "C", "goals": 0, "assists": 0, "points": 0, "plusMinus": 0, "pim": 0, "hits": 1, "powerPlayGoals": 0, "sog": 2, "faceoffWinningPctg": 0.666667, "toi": "16:51", "blockedShots": 0, "shifts": 21, "giveaways": 0, "takeaways": 2}, {"playerId": 8479066, "sweaterNumber": 94, "name": {"default": "R. Lomberg"}, "position": "L", "goals": 1, "assists": 0, "points": 1, "plusMinus": 1, "pim": 0, "hits": 1, "powerPlayGoals": 0, "sog": 3, "faceoffWinningPctg": 0.0, "toi": "14:37", "blockedShots": 0, "shifts": 21, "giveaways": 0, "takeaways": 1}], "defense": [{"playerId": 8482641, "sweaterNumber": 3, "name": {"default": "M. Kiersted"}, "position": "D", "goals": 0, "assists": 0, "points": 0, "plusMinus": 1, "pim": 0, "hits": 1, "powerPlayGoals": 0, "sog": 0, "faceoffWinningPctg": 0.0, "toi": "09:02", "blockedShots": 0, "shifts": 13, "giveaways": 0, "takeaways": 0}, {"playerId": 8477932, "sweaterNumber": 5, "name": {"default": "A. Ekblad"}, "position": "D", "goals": 0, "assists": 0, "points": 0, "plusMinus": -2, "pim": 2, "hits": 0, "powerPlayGoals": 0, "sog": 1, "faceoffWinningPctg": 0.0, "toi": "26:17", "blockedShots": 1, "shifts": 29, "giveaways": 3, "takeaways": 1}, {"playerId": 8471686, "sweaterNumber": 18, "name": {"default": "M. Staal"}, "position": "D", "goals": 0, "assists": 0, "points": 0, "plusMinus": 0, "pim": 0, "hits": 2, "powerPlayGoals": 0, "sog": 1, "faceoffWinningPctg": 0.0, "toi": "17:28", "blockedShots": 3, "shifts": 26, "giveaways": 1, "takeaways": 0}, {"playerId": 8479372, "sweaterNumber": 28, "name": {"default": "J. Mahura"}, "position": "D", "goals": 0, "assists": 0, "points": 0, "plusMinus": 1, "pim": 0, "hits": 1, "powerPlayGoals": 0, "sog": 1, "faceoffWinningPctg": 0.0, "toi": "15:46", "blockedShots": 0, "shifts": 20, "giveaways": 0, "takeaways": 1}, {"playerId": 8478055, "sweaterNumber": 42, "name": {"default": "G. Forsling"}, "position": "D", "goals": 0, "assists": 0, "points": 0, "plusMinus": 0, "pim": 0, "hits": 0, "powerPlayGoals": 0, "sog": 4, "faceoffWinningPctg": 0.0, "toi": "20:56", "blockedShots": 0, "shifts": 28, "giveaways": 0, "takeaways": 1}, {"playerId": 8477986, "sweaterNumber": 62, "name": {"default": "B. Montour"}, "position": "D", "goals": 0, "assists": 1, "points": 1, "plusMinus": 0, "pim": 0, "hits": 2, "powerPlayGoals": 0, "sog": 2, "faceoffWinningPctg": 0.0, "toi": "28:34", "blockedShots": 0, "shifts": 30, "giveaways": 0, "takeaways": 0}], "goalies": [{"playerId": 8481519, "sweaterNumber": 30, "name": {"default": "S. Knight"}, "position": "G", "evenStrengthShotsAgainst": "0/0", "powerPlayShotsAgainst": "0/0", "shorthandedShotsAgainst": "0/0", "saveShotsAgainst": "0/0", "evenStrengthGoalsAgainst": 0, "powerPlayGoalsAgainst": 0, "shorthandedGoalsAgainst": 0, "pim": 0, "goalsAgainst": 0, "toi": "00:00", "starter": false, "shotsAgainst": 0, "saves": 0}, {"playerId": 8475683, "sweaterNumber": 72, "name": {"default": "S. Bobrovsky", "cs": "S. Bobrovskij", "fi": "S. Bobrovski", "sk": "S. Bobrovskij"}, "position": "G", "evenStrengthShotsAgainst": "30/30", "powerPlayShotsAgainst": "3/5", "shorthandedShotsAgainst": "2/3", "saveShotsAgainst": "35/38", "savePctg": 0.921053, "evenStrengthGoalsAgainst": 0, "powerPlayGoalsAgainst": 2, "shorthandedGoalsAgainst": 1, "pim": 0, "goalsAgainst": 3, "toi": "59:06", "starter": true, "decision": "L", "shotsAgainst": 38, "saves": 35}]}}, "summary": {}, "gameOutcome": {"lastPeriodType": "REG"}}