{"id": 2020020405, "season": 20202021, "gameType": 2, "limitedScoring": false, "gameDate": "2021-03-09", "venue": {"default": "PPG Paints Arena"}, "venueLocation": {"default": "Pittsburgh"}, "startTimeUTC": "2021-03-09T23:00:00Z", "easternUTCOffset": "-05:00", "venueUTCOffset": "-05:00", "tvBroadcasts": [{"id": 241, "market": "N", "countryCode": "US", "network": "NBCSN", "sequenceNumber": 25}, {"id": 282, "market": "N", "countryCode": "CA", "network": "SN", "sequenceNumber": 107}, {"id": 316, "market": "H", "countryCode": "US", "network": "ATTSN-PT", "sequenceNumber": 214}, {"id": 27, "market": "A", "countryCode": "US", "network": "MSG", "sequenceNumber": 417}], "gameState": "OFF", "gameScheduleState": "OK", "periodDescriptor": {"number": 3, "periodType": "REG", "maxRegulationPeriods": 3}, "regPeriods": 3, "awayTeam": {"id": 3, "commonName": {"default": "Rangers"}, "abbrev": "NYR", "score": 2, "sog": 35, "logo": "https://assets.nhle.com/logos/nhl/svg/NYR_light.svg", "darkLogo": "https://assets.nhle.com/logos/nhl/svg/NYR_dark.svg", "placeName": {"default": "New York"}, "placeNameWithPreposition": {"default": "New York", "fr": "de New York"}}, "homeTeam": {"id": 5, "commonName": {"default": "Penguins"}, "abbrev": "PIT", "score": 4, "sog": 27, "logo": "https://assets.nhle.com/logos/nhl/svg/PIT_light.svg", "darkLogo": "https://assets.nhle.com/logos/nhl/svg/PIT_dark.svg", "placeName": {"default": "Pittsburgh"}, "placeNameWithPreposition": {"default": "Pittsburgh", "fr": "de Pittsburgh"}}, "clock": {"timeRemaining": "00:00", "secondsRemaining": 0, "running": false, "inIntermission": false}, "playerByGameStats": {"awayTeam": {"forwards": [{"playerId": 8479328, "sweaterNumber": 12, "name": {"default": "J. Gauthier"}, "position": "R", "goals": 0, "assists": 1, "points": 1, "plusMinus": -1, "pim": 0, "hits": 4, "powerPlayGoals": 0, "sog": 2, "faceoffWinningPctg": 1.0, "toi": "15:23", "blockedShots": 0, "shifts": 20, "giveaways": 0, "takeaways": 0}, {"playerId": 8482109, "sweaterNumber": 13, "name": {"default": "A. Lafreni\u00e8re"}, "position": "L", "goals": 0, "assists": 0, "points": 0, "plusMinus": -1, "pim": 0, "hits": 2, "powerPlayGoals": 0, "sog": 2, "faceoffWinningPctg": 0.5, "toi": "18:29", "blockedShots": 0, "shifts": 22, "giveaways": 0, "takeaways": 0}, {"playerId": 8476458, "sweaterNumber": 16, "name": {"default": "R. Strome"}, "position": "C", "goals": 1, "assists": 0, "points": 1, "plusMinus": -1, "pim": 0, "hits": 2, "powerPlayGoals": 1, "sog": 3, "faceoffWinningPctg": 0.466667, "toi": "17:08", "blockedShots": 0, "shifts": 23, "giveaways": 1, "takeaways": 1}, {"playerId": 8479291, "sweaterNumber": 17, "name": {"default": "K. Rooney"}, "position": "C", "goals": 0, "assists": 0, "points": 0, "plusMinus": -1, "pim": 0, "hits": 7, "powerPlayGoals": 0, "sog": 1, "faceoffWinningPctg": 0.727273, "toi": "12:55", "blockedShots": 0, "shifts": 19, "giveaways": 0, "takeaways": 0}, {"playerId": 8475184, "sweaterNumber": 20, "name": {"default": "C. Kreider"}, "position": "L", "goals": 0, "assists": 1, "points": 1, "plusMinus": 0, "pim": 0, "hits": 6, "powerPlayGoals": 0, "sog": 1, "faceoffWinningPctg": 0.0, "toi": "16:00", "blockedShots": 1, "shifts": 23, "giveaways": 0, "takeaways": 0}, {"playerId": 8479353, "sweaterNumber": 21, "name": {"default": "B. Howden"}, "position": "C", "goals": 0, "assists": 0, "points": 0, "plusMinus": -1, "pim": 0, "hits": 2, "powerPlayGoals": 0, "sog": 0, "faceoffWinningPctg": 0.636364, "toi": "12:35", "blockedShots": 1, "shifts": 17, "giveaways": 0, "takeaways": 0}, {"playerId": 8481554, "sweaterNumber": 24, "name": {"default": "K. Kakko"}, "position": "R", "goals": 0, "assists": 0, "points": 0, "plusMinus": -1, "pim": 0, "hits": 1, "powerPlayGoals": 0, "sog": 3, "faceoffWinningPctg": 0.0, "toi": "16:10", "blockedShots": 1, "shifts": 22, "giveaways": 0, "takeaways": 1}, {"playerId": 8476858, "sweaterNumber": 33, "name": {"default": "P. Di Giuseppe"}, "position": "L", "goals": 0, "assists": 0, "points": 0, "plusMinus": -1, "pim": 0, "hits": 7, "powerPlayGoals": 0, "sog": 0, "faceoffWinningPctg": 0.0, "toi": "11:19", "blockedShots": 0, "shifts": 16, "giveaways": 0, "takeaways": 0}, {"playerId": 8476278, "sweaterNumber": 43, "name": {"default": "C. Blackwell"}, "position": "C", "goals": 0, "assists": 0, "points": 0, "plusMinus": 0, "pim": 0, "hits": 3, "powerPlayGoals": 0, "sog": 3, "faceoffWinningPctg": 1.0, "toi": "13:00", "blockedShots": 0, "shifts": 16, "giveaways": 0, "takeaways": 0}, {"playerId": 8480078, "sweaterNumber": 72, "name": {"default": "F. Chytil"}, "position": "C", "goals": 0, "assists": 0, "points": 0, "plusMinus": -2, "pim": 0, "hits": 0, "powerPlayGoals": 0, "sog": 3, "faceoffWinningPctg": 0.0, "toi": "13:05", "blockedShots": 1, "shifts": 18, "giveaways": 0, "takeaways": 1}, {"playerId": 8477402, "sweaterNumber": 89, "name": {"default": "P. Buchnevich", "cs": "P. Bu\u010dn\u011bvi\u010d", "fi": "P. Butshnevitsh", "sk": "P. Bu\u010dn\u011bvi\u010d"}, "position": "L", "goals": 0, "assists": 1, "points": 1, "plusMinus": -1, "pim": 0, "hits": 1, "powerPlayGoals": 0, "sog": 3, "faceoffWinningPctg": 0.0, "toi": "16:40", "blockedShots": 1, "shifts": 23, "giveaways": 1, "takeaways": 0}, {"playerId": 8476459, "sweaterNumber": 93, "name": {"default": "M. Zibanejad"}, "position": "C", "goals": 0, "assists": 0, "points": 0, "plusMinus": -1, "pim": 0, "hits": 3, "powerPlayGoals": 0, "sog": 6, "faceoffWinningPctg": 0.444444, "toi": "20:03", "blockedShots": 1, "shifts": 23, "giveaways": 0, "takeaways": 0}], "defense": [{"playerId": 8476885, "sweaterNumber": 8, "name": {"default": "J. Trouba"}, "position": "D", "goals": 0, "assists": 0, "points": 0, "plusMinus": -1, "pim": 0, "hits": 3, "powerPlayGoals": 0, "sog": 1, "faceoffWinningPctg": 0.0, "toi": "20:48", "blockedShots": 1, "shifts": 25, "giveaways": 0, "takeaways": 0}, {"playerId": 8479323, "sweaterNumber": 23, "name": {"default": "A. Fox"}, "position": "D", "goals": 0, "assists": 1, "points": 1, "plusMinus": -2, "pim": 0, "hits": 1, "powerPlayGoals": 0, "sog": 2, "faceoffWinningPctg": 0.0, "toi": "22:52", "blockedShots": 1, "shifts": 27, "giveaways": 0, "takeaways": 0}, {"playerId": 8471677, "sweaterNumber": 27, "name": {"default": "J. Johnson"}, "position": "D", "goals": 1, "assists": 0, "points": 1, "plusMinus": 0, "pim": 0, "hits": 1, "powerPlayGoals": 0, "sog": 2, "faceoffWinningPctg": 0.0, "toi": "16:33", "blockedShots": 1, "shifts": 20, "giveaways": 0, "takeaways": 0}, {"playerId": 8474090, "sweaterNumber": 42, "name": {"default": "B. Smith"}, "position": "D", "goals": 0, "assists": 0, "points": 0, "plusMinus": 1, "pim": 2, "hits": 4, "powerPlayGoals": 0, "sog": 1, "faceoffWinningPctg": 0.0, "toi": "16:27", "blockedShots": 0, "shifts": 20, "giveaways": 0, "takeaways": 0}, {"playerId": 8479324, "sweaterNumber": 55, "name": {"default": "R. Lindgren"}, "position": "D", "goals": 0, "assists": 0, "points": 0, "plusMinus": -2, "pim": 0, "hits": 6, "powerPlayGoals": 0, "sog": 2, "faceoffWinningPctg": 0.0, "toi": "19:06", "blockedShots": 1, "shifts": 24, "giveaways": 0, "takeaways": 1}, {"playerId": 8480817, "sweaterNumber": 79, "name": {"default": "K. Miller"}, "position": "D", "goals": 0, "assists": 0, "points": 0, "plusMinus": -1, "pim": 0, "hits": 5, "powerPlayGoals": 0, "sog": 0, "faceoffWinningPctg": 0.0, "toi": "21:02", "blockedShots": 1, "shifts": 26, "giveaways": 0, "takeaways": 0}], "goalies": [{"playerId": 8480382, "sweaterNumber": 40, "name": {"default": "A. Georgiev", "cs": "A. Georgijev", "fi": "A. Georgijev", "sk": "A. Georgijev"}, "position": "G", "evenStrengthShotsAgainst": "0/0", "powerPlayShotsAgainst": "0/0", "shorthandedShotsAgainst": "0/0", "saveShotsAgainst": "0/0", "evenStrengthGoalsAgainst": 0, "powerPlayGoalsAgainst": 0, "shorthandedGoalsAgainst": 0, "pim": 0, "goalsAgainst": 0, "toi": "00:00", "starter": false, "shotsAgainst": 0, "saves": 0}, {"playerId": 8476234, "sweaterNumber": 71, "name": {"default": "K. Kinkaid"}, "position": "G", "evenStrengthShotsAgainst": "18/20", "powerPlayShotsAgainst": "4/4", "shorthandedShotsAgainst": "1/2", "saveShotsAgainst": "23/26", "savePctg": 0.884615, "evenStrengthGoalsAgainst": 2, "powerPlayGoalsAgainst": 0, "shorthandedGoalsAgainst": 1, "pim": 0, "goalsAgainst": 3, "toi": "58:25", "starter": true, "decision": "L", "shotsAgainst": 26, "saves": 23}]}, "homeTeam": {"forwards": [{"playerId": 8474098, "sweaterNumber": 7, "name": {"default": "C. Sceviour"}, "position": "C", "goals": 0, "assists": 0, "points": 0, "plusMinus": 0, "pim": 0, "hits": 2, "powerPlayGoals": 0, "sog": 0, "faceoffWinningPctg": 0.0, "toi": "07:39", "blockedShots": 2, "shifts": 11, "giveaways": 1, "takeaways": 1}, {"playerId": 8478542, "sweaterNumber": 9, "name": {"default": "E. Rodrigues"}, "position": "C", "goals": 0, "assists": 1, "points": 1, "plusMinus": 1, "pim": 0, "hits": 2, "powerPlayGoals": 0, "sog": 1, "faceoffWinningPctg": 0.4, "toi": "16:54", "blockedShots": 0, "shifts": 23, "giveaways": 0, "takeaways": 0}, {"playerId": 8479944, "sweaterNumber": 12, "name": {"default": "Z. Aston-Reese"}, "position": "L", "goals": 0, "assists": 0, "points": 0, "plusMinus": -1, "pim": 0, "hits": 1, "powerPlayGoals": 0, "sog": 1, "faceoffWinningPctg": 0.0, "toi": "12:42", "blockedShots": 0, "shifts": 18, "giveaways": 0, "takeaways": 0}, {"playerId": 8479293, "sweaterNumber": 13, "name": {"default": "B. Tanev"}, "position": "L", "goals": 0, "assists": 1, "points": 1, "plusMinus": 1, "pim": 0, "hits": 4, "powerPlayGoals": 0, "sog": 1, "faceoffWinningPctg": 0.5, "toi": "14:14", "blockedShots": 1, "shifts": 24, "giveaways": 0, "takeaways": 0}, {"playerId": 8476873, "sweaterNumber": 14, "name": {"default": "M. Jankowski"}, "position": "L", "goals": 0, "assists": 0, "points": 0, "plusMinus": 0, "pim": 0, "hits": 2, "powerPlayGoals": 0, "sog": 2, "faceoffWinningPctg": 0.5, "toi": "09:00", "blockedShots": 1, "shifts": 16, "giveaways": 0, "takeaways": 0}, {"playerId": 8475810, "sweaterNumber": 17, "name": {"default": "B. Rust"}, "position": "R", "goals": 0, "assists": 0, "points": 0, "plusMinus": 2, "pim": 0, "hits": 1, "powerPlayGoals": 0, "sog": 6, "faceoffWinningPctg": 1.0, "toi": "19:27", "blockedShots": 1, "shifts": 25, "giveaways": 0, "takeaways": 1}, {"playerId": 8477953, "sweaterNumber": 42, "name": {"default": "K. Kapanen"}, "position": "R", "goals": 1, "assists": 0, "points": 1, "plusMinus": 0, "pim": 0, "hits": 3, "powerPlayGoals": 0, "sog": 1, "faceoffWinningPctg": 0.0, "toi": "16:58", "blockedShots": 0, "shifts": 23, "giveaways": 2, "takeaways": 0}, {"playerId": 8476927, "sweaterNumber": 53, "name": {"default": "T. Blueger", "cs": "T. Blugers", "sk": "T. Blugers"}, "position": "C", "goals": 1, "assists": 0, "points": 1, "plusMinus": 0, "pim": 0, "hits": 0, "powerPlayGoals": 0, "sog": 2, "faceoffWinningPctg": 0.642857, "toi": "15:37", "blockedShots": 2, "shifts": 24, "giveaways": 0, "takeaways": 0}, {"playerId": 8478074, "sweaterNumber": 57, "name": {"default": "A. Angello"}, "position": "C", "goals": 0, "assists": 0, "points": 0, "plusMinus": 0, "pim": 0, "hits": 6, "powerPlayGoals": 0, "sog": 1, "faceoffWinningPctg": 0.0, "toi": "08:12", "blockedShots": 1, "shifts": 13, "giveaways": 0, "takeaways": 0}, {"playerId": 8477404, "sweaterNumber": 59, "name": {"default": "J. Guentzel"}, "position": "C", "goals": 1, "assists": 0, "points": 1, "plusMinus": 2, "pim": 0, "hits": 1, "powerPlayGoals": 0, "sog": 2, "faceoffWinningPctg": 0.0, "toi": "19:34", "blockedShots": 1, "shifts": 25, "giveaways": 0, "takeaways": 0}, {"playerId": 8471215, "sweaterNumber": 71, "name": {"default": "E. Malkin"}, "position": "C", "goals": 0, "assists": 1, "points": 1, "plusMinus": 1, "pim": 0, "hits": 2, "powerPlayGoals": 0, "sog": 1, "faceoffWinningPctg": 0.285714, "toi": "18:53", "blockedShots": 1, "shifts": 23, "giveaways": 2, "takeaways": 2}, {"playerId": 8471675, "sweaterNumber": 87, "name": {"default": "S. Crosby"}, "position": "C", "goals": 1, "assists": 1, "points": 2, "plusMinus": 2, "pim": 2, "hits": 0, "powerPlayGoals": 0, "sog": 1, "faceoffWinningPctg": 0.421053, "toi": "19:16", "blockedShots": 0, "shifts": 25, "giveaways": 1, "takeaways": 2}], "defense": [{"playerId": 8476879, "sweaterNumber": 4, "name": {"default": "C. Ceci"}, "position": "D", "goals": 0, "assists": 0, "points": 0, "plusMinus": 0, "pim": 0, "hits": 2, "powerPlayGoals": 0, "sog": 1, "faceoffWinningPctg": 0.0, "toi": "16:53", "blockedShots": 2, "shifts": 23, "giveaways": 0, "takeaways": 0}, {"playerId": 8476875, "sweaterNumber": 5, "name": {"default": "M. Matheson"}, "position": "D", "goals": 0, "assists": 0, "points": 0, "plusMinus": -1, "pim": 2, "hits": 1, "powerPlayGoals": 0, "sog": 2, "faceoffWinningPctg": 0.0, "toi": "17:27", "blockedShots": 1, "shifts": 21, "giveaways": 0, "takeaways": 1}, {"playerId": 8478507, "sweaterNumber": 6, "name": {"default": "J. Marino"}, "position": "D", "goals": 0, "assists": 0, "points": 0, "plusMinus": 1, "pim": 0, "hits": 1, "powerPlayGoals": 0, "sog": 1, "faceoffWinningPctg": 0.0, "toi": "19:19", "blockedShots": 2, "shifts": 25, "giveaways": 0, "takeaways": 0}, {"playerId": 8475208, "sweaterNumber": 8, "name": {"default": "B. Dumoulin"}, "position": "D", "goals": 0, "assists": 1, "points": 1, "plusMinus": 3, "pim": 0, "hits": 6, "powerPlayGoals": 0, "sog": 1, "faceoffWinningPctg": 0.0, "toi": "22:44", "blockedShots": 3, "shifts": 29, "giveaways": 1, "takeaways": 0}, {"playerId": 8477969, "sweaterNumber": 28, "name": {"default": "M. Pettersson"}, "position": "D", "goals": 0, "assists": 0, "points": 0, "plusMinus": 1, "pim": 0, "hits": 1, "powerPlayGoals": 0, "sog": 0, "faceoffWinningPctg": 0.0, "toi": "15:49", "blockedShots": 2, "shifts": 20, "giveaways": 1, "takeaways": 2}, {"playerId": 8471724, "sweaterNumber": 58, "name": {"default": "K. Letang"}, "position": "D", "goals": 0, "assists": 0, "points": 0, "plusMinus": 2, "pim": 0, "hits": 2, "powerPlayGoals": 0, "sog": 3, "faceoffWinningPctg": 0.0, "toi": "25:15", "blockedShots": 3, "shifts": 30, "giveaways": 0, "takeaways": 0}], "goalies": [{"playerId": 8479193, "sweaterNumber": 1, "name": {"default": "C. DeSmith"}, "position": "G", "evenStrengthShotsAgainst": "0/0", "powerPlayShotsAgainst": "0/0", "shorthandedShotsAgainst": "0/0", "saveShotsAgainst": "0/0", "evenStrengthGoalsAgainst": 0, "powerPlayGoalsAgainst": 0, "shorthandedGoalsAgainst": 0, "pim": 0, "goalsAgainst": 0, "toi": "00:00", "starter": false, "shotsAgainst": 0, "saves": 0}, {"playerId": 8477465, "sweaterNumber": 35, "name": {"default": "T. Jarry"}, "position": "G", "evenStrengthShotsAgainst": "29/30", "powerPlayShotsAgainst": "2/3", "shorthandedShotsAgainst": "2/2", "saveShotsAgainst": "33/35", "savePctg": 0.942857, "evenStrengthGoalsAgainst": 1, "powerPlayGoalsAgainst": 1, "shorthandedGoalsAgainst": 0, "pim": 0, "goalsAgainst": 2, "toi": "60:00", "starter": true, "decision": "W", "shotsAgainst": 35, "saves": 33}]}}, "summary": {}, "gameOutcome": {"lastPeriodType": "REG"}}