{"id": 2022020590, "season": 20222023, "gameType": 2, "limitedScoring": false, "gameDate": "2023-01-01", "venue": {"default": "Prudential Center"}, "venueLocation": {"default": "Newark"}, "startTimeUTC": "2023-01-01T20:00:00Z", "easternUTCOffset": "-05:00", "venueUTCOffset": "-05:00", "tvBroadcasts": [{"id": 282, "market": "N", "countryCode": "CA", "network": "SN", "sequenceNumber": 107}, {"id": 375, "market": "A", "countryCode": "US", "network": "BSSO", "sequenceNumber": 399}, {"id": 409, "market": "H", "countryCode": "US", "network": "MSGSN", "sequenceNumber": 411}], "gameState": "OFF", "gameScheduleState": "OK", "periodDescriptor": {"number": 5, "periodType": "SO", "maxRegulationPeriods": 3}, "regPeriods": 3, "awayTeam": {"id": 12, "commonName": {"default": "Hurricanes"}, "abbrev": "CAR", "score": 5, "sog": 47, "logo": "https://assets.nhle.com/logos/nhl/svg/CAR_light.svg", "darkLogo": "https://assets.nhle.com/logos/nhl/svg/CAR_dark.svg", "placeName": {"default": "Carolina", "fr": "Caroline"}, "placeNameWithPreposition": {"default": "Carolina", "fr": "de la Caroline"}}, "homeTeam": {"id": 1, "commonName": {"default": "Devils"}, "abbrev": "NJD", "score": 4, "sog": 28, "logo": "https://assets.nhle.com/logos/nhl/svg/NJD_light.svg", "darkLogo": "https://assets.nhle.com/logos/nhl/svg/NJD_dark.svg", "placeName": {"default": "New Jersey"}, "placeNameWithPreposition": {"default": "New Jersey", "fr": "du New Jersey"}}, "clock": {"timeRemaining": "00:00", "secondsRemaining": 0, "running": false, "inIntermission": false}, "playerByGameStats": {"awayTeam": {"forwards": [{"playerId": 8473533, "sweaterNumber": 11, "name": {"default": "J. Staal"}, "position": "C", "goals": 0, "assists": 0, "points": 0, "plusMinus": 0, "pim": 0, "hits": 1, "powerPlayGoals": 0, "sog": 2, "faceoffWinningPctg": 0.636364, "toi": "16:56", "blockedShots": 0, "shifts": 27, "giveaways": 0, "takeaways": 1}, {"playerId": 8478427, "sweaterNumber": 20, "name": {"default": "S. Aho"}, "position": "C", "goals": 1, "assists": 1, "points": 2, "plusMinus": -2, "pim": 0, "hits": 0, "powerPlayGoals": 0, "sog": 5, "faceoffWinningPctg": 0.5, "toi": "20:17", "blockedShots": 1, "shifts": 25, "giveaways": 2, "takeaways": 2}, {"playerId": 8474613, "sweaterNumber": 21, "name": {"default": "D. Stepan"}, "position": "C", "goals": 2, "assists": 0, "points": 2, "plusMinus": 2, "pim": 0, "hits": 0, "powerPlayGoals": 0, "sog": 4, "faceoffWinningPctg": 0.0, "toi": "09:45", "blockedShots": 0, "shifts": 14, "giveaways": 0, "takeaways": 0}, {"playerId": 8476474, "sweaterNumber": 23, "name": {"default": "S. Noesen"}, "position": "R", "goals": 0, "assists": 2, "points": 2, "plusMinus": 2, "pim": 0, "hits": 1, "powerPlayGoals": 0, "sog": 1, "faceoffWinningPctg": 1.0, "toi": "11:35", "blockedShots": 0, "shifts": 16, "giveaways": 1, "takeaways": 0}, {"playerId": 8482093, "sweaterNumber": 24, "name": {"default": "S. Jarvis"}, "position": "C", "goals": 0, "assists": 0, "points": 0, "plusMinus": -3, "pim": 0, "hits": 0, "powerPlayGoals": 0, "sog": 4, "faceoffWinningPctg": 0.0, "toi": "16:49", "blockedShots": 1, "shifts": 20, "giveaways": 3, "takeaways": 0}, {"playerId": 8471669, "sweaterNumber": 26, "name": {"default": "P. Stastny"}, "position": "C", "goals": 0, "assists": 0, "points": 0, "plusMinus": 0, "pim": 0, "hits": 0, "powerPlayGoals": 0, "sog": 1, "faceoffWinningPctg": 0.631579, "toi": "15:24", "blockedShots": 1, "shifts": 19, "giveaways": 0, "takeaways": 0}, {"playerId": 8480830, "sweaterNumber": 37, "name": {"default": "A. Svechnikov", "cs": "A. Sve\u010dnikov", "fi": "A. Svetshnikov", "sk": "A. Sve\u010dnikov"}, "position": "R", "goals": 0, "assists": 0, "points": 0, "plusMinus": 0, "pim": 0, "hits": 3, "powerPlayGoals": 0, "sog": 7, "faceoffWinningPctg": 0.0, "toi": "19:54", "blockedShots": 0, "shifts": 24, "giveaways": 0, "takeaways": 0}, {"playerId": 8476921, "sweaterNumber": 48, "name": {"default": "J. Martinook"}, "position": "L", "goals": 0, "assists": 0, "points": 0, "plusMinus": -1, "pim": 0, "hits": 1, "powerPlayGoals": 0, "sog": 1, "faceoffWinningPctg": 0.0, "toi": "15:52", "blockedShots": 0, "shifts": 24, "giveaways": 0, "takeaways": 0}, {"playerId": 8475855, "sweaterNumber": 71, "name": {"default": "J. Fast", "cs": "J. Fasth", "de": "J. Fasth", "fi": "J. Fasth", "sk": "J. Fasth", "sv": "J. Fasth"}, "position": "R", "goals": 0, "assists": 0, "points": 0, "plusMinus": -1, "pim": 0, "hits": 1, "powerPlayGoals": 0, "sog": 1, "faceoffWinningPctg": 0.0, "toi": "14:01", "blockedShots": 0, "shifts": 21, "giveaways": 0, "takeaways": 0}, {"playerId": 8480829, "sweaterNumber": 82, "name": {"default": "J. Kotkaniemi"}, "position": "C", "goals": 0, "assists": 1, "points": 1, "plusMinus": 1, "pim": 0, "hits": 1, "powerPlayGoals": 0, "sog": 0, "faceoffWinningPctg": 0.75, "toi": "11:07", "blockedShots": 0, "shifts": 14, "giveaways": 1, "takeaways": 0}, {"playerId": 8476882, "sweaterNumber": 86, "name": {"default": "T. Teravainen", "cs": "T. Ter\u00e4v\u00e4inen", "fi": "T. Ter\u00e4v\u00e4inen", "sk": "T. Ter\u00e4v\u00e4inen", "sv": "T. Ter\u00e4v\u00e4inen"}, "position": "C", "goals": 0, "assists": 0, "points": 0, "plusMinus": -1, "pim": 2, "hits": 0, "powerPlayGoals": 0, "sog": 1, "faceoffWinningPctg": 0.0, "toi": "15:58", "blockedShots": 0, "shifts": 21, "giveaways": 2, "takeaways": 0}, {"playerId": 8480039, "sweaterNumber": 88, "name": {"default": "M. Necas", "cs": "M. Ne\u010das", "sk": "M. Ne\u010das"}, "position": "C", "goals": 1, "assists": 0, "points": 1, "plusMinus": 0, "pim": 2, "hits": 0, "powerPlayGoals": 1, "sog": 3, "faceoffWinningPctg": 0.833333, "toi": "19:23", "blockedShots": 0, "shifts": 23, "giveaways": 1, "takeaways": 0}], "defense": [{"playerId": 8478970, "sweaterNumber": 5, "name": {"default": "J. Chatfield"}, "position": "D", "goals": 0, "assists": 0, "points": 0, "plusMinus": 2, "pim": 0, "hits": 0, "powerPlayGoals": 0, "sog": 1, "faceoffWinningPctg": 0.0, "toi": "12:45", "blockedShots": 0, "shifts": 17, "giveaways": 0, "takeaways": 0}, {"playerId": 8470613, "sweaterNumber": 8, "name": {"default": "B. Burns"}, "position": "D", "goals": 0, "assists": 1, "points": 1, "plusMinus": -1, "pim": 0, "hits": 0, "powerPlayGoals": 0, "sog": 7, "faceoffWinningPctg": 0.0, "toi": "25:47", "blockedShots": 1, "shifts": 31, "giveaways": 1, "takeaways": 0}, {"playerId": 8477488, "sweaterNumber": 22, "name": {"default": "B. Pesce"}, "position": "D", "goals": 0, "assists": 0, "points": 0, "plusMinus": -2, "pim": 2, "hits": 0, "powerPlayGoals": 0, "sog": 1, "faceoffWinningPctg": 0.0, "toi": "24:47", "blockedShots": 1, "shifts": 31, "giveaways": 1, "takeaways": 0}, {"playerId": 8475177, "sweaterNumber": 44, "name": {"default": "C. de Haan"}, "position": "D", "goals": 0, "assists": 1, "points": 1, "plusMinus": 1, "pim": 0, "hits": 0, "powerPlayGoals": 0, "sog": 0, "faceoffWinningPctg": 0.0, "toi": "12:23", "blockedShots": 0, "shifts": 17, "giveaways": 0, "takeaways": 0}, {"playerId": 8476958, "sweaterNumber": 74, "name": {"default": "J. Slavin"}, "position": "D", "goals": 0, "assists": 0, "points": 0, "plusMinus": -2, "pim": 0, "hits": 0, "powerPlayGoals": 0, "sog": 3, "faceoffWinningPctg": 0.0, "toi": "22:32", "blockedShots": 1, "shifts": 30, "giveaways": 0, "takeaways": 0}, {"playerId": 8476869, "sweaterNumber": 76, "name": {"default": "B. Skjei"}, "position": "D", "goals": 0, "assists": 0, "points": 0, "plusMinus": 0, "pim": 2, "hits": 2, "powerPlayGoals": 0, "sog": 5, "faceoffWinningPctg": 0.0, "toi": "21:45", "blockedShots": 2, "shifts": 31, "giveaways": 0, "takeaways": 0}], "goalies": [{"playerId": 8477293, "sweaterNumber": 32, "name": {"default": "A. Raanta"}, "position": "G", "evenStrengthShotsAgainst": "18/22", "powerPlayShotsAgainst": "6/6", "shorthandedShotsAgainst": "0/0", "saveShotsAgainst": "24/28", "savePctg": 0.857143, "evenStrengthGoalsAgainst": 4, "powerPlayGoalsAgainst": 0, "shorthandedGoalsAgainst": 0, "pim": 0, "goalsAgainst": 4, "toi": "65:00", "starter": true, "decision": "W", "shotsAgainst": 28, "saves": 24}, {"playerId": 8481611, "sweaterNumber": 52, "name": {"default": "P. Kochetkov", "fi": "P. Kotshetkov"}, "position": "G", "evenStrengthShotsAgainst": "0/0", "powerPlayShotsAgainst": "0/0", "shorthandedShotsAgainst": "0/0", "saveShotsAgainst": "0/0", "evenStrengthGoalsAgainst": 0, "powerPlayGoalsAgainst": 0, "shorthandedGoalsAgainst": 0, "pim": 0, "goalsAgainst": 0, "toi": "00:00", "starter": false, "shotsAgainst": 0, "saves": 0}]}, "homeTeam": {"forwards": [{"playerId": 8481740, "sweaterNumber": 12, "name": {"default": "T. Thompson"}, "position": "R", "goals": 0, "assists": 0, "points": 0, "plusMinus": 0, "pim": 0, "hits": 0, "powerPlayGoals": 0, "sog": 1, "faceoffWinningPctg": 0.0, "toi": "07:25", "blockedShots": 1, "shifts": 11, "giveaways": 1, "takeaways": 0}, {"playerId": 8480002, "sweaterNumber": 13, "name": {"default": "N. Hischier"}, "position": "C", "goals": 1, "assists": 0, "points": 1, "plusMinus": 2, "pim": 0, "hits": 0, "powerPlayGoals": 0, "sog": 4, "faceoffWinningPctg": 0.56, "toi": "18:58", "blockedShots": 2, "shifts": 28, "giveaways": 2, "takeaways": 2}, {"playerId": 8481068, "sweaterNumber": 17, "name": {"default": "Y. Sharangovich", "cs": "J. \u0160arangovi\u010d", "fi": "J. Sharanhovitsh", "sk": "J. \u0160arangovi\u010d"}, "position": "C", "goals": 0, "assists": 0, "points": 0, "plusMinus": -1, "pim": 0, "hits": 1, "powerPlayGoals": 0, "sog": 3, "faceoffWinningPctg": 0.5, "toi": "14:16", "blockedShots": 1, "shifts": 16, "giveaways": 3, "takeaways": 1}, {"playerId": 8479415, "sweaterNumber": 20, "name": {"default": "M. McLeod"}, "position": "C", "goals": 0, "assists": 0, "points": 0, "plusMinus": -1, "pim": 0, "hits": 0, "powerPlayGoals": 0, "sog": 2, "faceoffWinningPctg": 0.368421, "toi": "14:59", "blockedShots": 1, "shifts": 22, "giveaways": 1, "takeaways": 1}, {"playerId": 8477425, "sweaterNumber": 44, "name": {"default": "M. Wood"}, "position": "L", "goals": 0, "assists": 0, "points": 0, "plusMinus": -1, "pim": 0, "hits": 1, "powerPlayGoals": 0, "sog": 0, "faceoffWinningPctg": 0.0, "toi": "12:44", "blockedShots": 0, "shifts": 17, "giveaways": 2, "takeaways": 0}, {"playerId": 8480188, "sweaterNumber": 49, "name": {"default": "F. Zetterlund"}, "position": "L", "goals": 0, "assists": 0, "points": 0, "plusMinus": -2, "pim": 0, "hits": 0, "powerPlayGoals": 0, "sog": 0, "faceoffWinningPctg": 0.0, "toi": "11:00", "blockedShots": 0, "shifts": 13, "giveaways": 2, "takeaways": 0}, {"playerId": 8475287, "sweaterNumber": 56, "name": {"default": "E. Haula"}, "position": "L", "goals": 0, "assists": 1, "points": 1, "plusMinus": 1, "pim": 0, "hits": 1, "powerPlayGoals": 0, "sog": 0, "faceoffWinningPctg": 0.409091, "toi": "18:56", "blockedShots": 2, "shifts": 29, "giveaways": 2, "takeaways": 0}, {"playerId": 8479407, "sweaterNumber": 63, "name": {"default": "J. Bratt"}, "position": "L", "goals": 2, "assists": 1, "points": 3, "plusMinus": 2, "pim": 0, "hits": 0, "powerPlayGoals": 0, "sog": 2, "faceoffWinningPctg": 0.0, "toi": "17:55", "blockedShots": 0, "shifts": 25, "giveaways": 1, "takeaways": 0}, {"playerId": 8480003, "sweaterNumber": 70, "name": {"default": "J. Boqvist"}, "position": "C", "goals": 0, "assists": 0, "points": 0, "plusMinus": -1, "pim": 0, "hits": 0, "powerPlayGoals": 0, "sog": 0, "faceoffWinningPctg": 0.0, "toi": "10:24", "blockedShots": 0, "shifts": 13, "giveaways": 1, "takeaways": 0}, {"playerId": 8481559, "sweaterNumber": 86, "name": {"default": "J. Hughes"}, "position": "C", "goals": 1, "assists": 0, "points": 1, "plusMinus": 0, "pim": 0, "hits": 0, "powerPlayGoals": 0, "sog": 6, "faceoffWinningPctg": 0.0, "toi": "22:22", "blockedShots": 0, "shifts": 28, "giveaways": 3, "takeaways": 1}, {"playerId": 8475193, "sweaterNumber": 90, "name": {"default": "T. Tatar"}, "position": "L", "goals": 0, "assists": 2, "points": 2, "plusMinus": 1, "pim": 0, "hits": 1, "powerPlayGoals": 0, "sog": 1, "faceoffWinningPctg": 0.0, "toi": "17:21", "blockedShots": 3, "shifts": 25, "giveaways": 0, "takeaways": 1}, {"playerId": 8482110, "sweaterNumber": 91, "name": {"default": "D. Mercer"}, "position": "C", "goals": 0, "assists": 1, "points": 1, "plusMinus": 1, "pim": 2, "hits": 0, "powerPlayGoals": 0, "sog": 2, "faceoffWinningPctg": 0.333333, "toi": "19:52", "blockedShots": 3, "shifts": 28, "giveaways": 1, "takeaways": 0}], "defense": [{"playerId": 8474090, "sweaterNumber": 2, "name": {"default": "B. Smith"}, "position": "D", "goals": 0, "assists": 0, "points": 0, "plusMinus": -1, "pim": 0, "hits": 0, "powerPlayGoals": 0, "sog": 0, "faceoffWinningPctg": 0.0, "toi": "18:38", "blockedShots": 2, "shifts": 17, "giveaways": 2, "takeaways": 0}, {"playerId": 8476462, "sweaterNumber": 7, "name": {"default": "D. Hamilton"}, "position": "D", "goals": 0, "assists": 1, "points": 1, "plusMinus": 2, "pim": 0, "hits": 2, "powerPlayGoals": 0, "sog": 4, "faceoffWinningPctg": 0.0, "toi": "23:46", "blockedShots": 1, "shifts": 29, "giveaways": 3, "takeaways": 0}, {"playerId": 8476923, "sweaterNumber": 28, "name": {"default": "D. Severson"}, "position": "D", "goals": 0, "assists": 0, "points": 0, "plusMinus": 1, "pim": 4, "hits": 1, "powerPlayGoals": 0, "sog": 1, "faceoffWinningPctg": 0.0, "toi": "24:29", "blockedShots": 2, "shifts": 32, "giveaways": 0, "takeaways": 0}, {"playerId": 8477435, "sweaterNumber": 33, "name": {"default": "R. Graves"}, "position": "D", "goals": 0, "assists": 1, "points": 1, "plusMinus": 2, "pim": 2, "hits": 3, "powerPlayGoals": 0, "sog": 2, "faceoffWinningPctg": 0.0, "toi": "18:03", "blockedShots": 3, "shifts": 25, "giveaways": 4, "takeaways": 1}, {"playerId": 8478399, "sweaterNumber": 71, "name": {"default": "J. Siegenthaler"}, "position": "D", "goals": 0, "assists": 0, "points": 0, "plusMinus": 1, "pim": 2, "hits": 2, "powerPlayGoals": 0, "sog": 0, "faceoffWinningPctg": 0.0, "toi": "21:44", "blockedShots": 4, "shifts": 29, "giveaways": 0, "takeaways": 1}, {"playerId": 8480860, "sweaterNumber": 88, "name": {"default": "K. Bahl"}, "position": "D", "goals": 0, "assists": 0, "points": 0, "plusMinus": -2, "pim": 0, "hits": 0, "powerPlayGoals": 0, "sog": 0, "faceoffWinningPctg": 0.0, "toi": "12:48", "blockedShots": 1, "shifts": 17, "giveaways": 0, "takeaways": 0}], "goalies": [{"playerId": 8478406, "sweaterNumber": 29, "name": {"default": "M. Blackwood"}, "position": "G", "evenStrengthShotsAgainst": "34/36", "powerPlayShotsAgainst": "7/8", "shorthandedShotsAgainst": "2/3", "saveShotsAgainst": "43/47", "savePctg": 0.914894, "evenStrengthGoalsAgainst": 2, "powerPlayGoalsAgainst": 1, "shorthandedGoalsAgainst": 1, "pim": 0, "goalsAgainst": 4, "toi": "65:00", "starter": true, "decision": "O", "shotsAgainst": 47, "saves": 43}, {"playerId": 8477970, "sweaterNumber": 41, "name": {"default": "V. Vanecek", "cs": "V. Van\u011b\u010dek", "sk": "V. Van\u011b\u010dek"}, "position": "G", "evenStrengthShotsAgainst": "0/0", "powerPlayShotsAgainst": "0/0", "shorthandedShotsAgainst": "0/0", "saveShotsAgainst": "0/0", "evenStrengthGoalsAgainst": 0, "powerPlayGoalsAgainst": 0, "shorthandedGoalsAgainst": 0, "pim": 0, "goalsAgainst": 0, "toi": "00:00", "starter": false, "shotsAgainst": 0, "saves": 0}]}}, "summary": {}, "gameOutcome": {"lastPeriodType": "SO"}}