{"previousStartDate": "2026-01-01", "nextStartDate": "2026-01-15", "calendarUrl": "https://nhl.ecal.com/rangers", "clubTimezone": "America/New_York", "clubUTCOffset": "-05:00", "games": [{"id": 2025020685, "season": 20252026, "gameType": 2, "gameDate": "2026-01-08", "venue": {"default": "Madison Square Garden"}, "neutralSite": false, "startTimeUTC": "2026-01-09T00:00:00Z", "easternUTCOffset": "-05:00", "venueUTCOffset": "-05:00", "venueTimezone": "America/New_York", "gameState": "OFF", "gameScheduleState": "OK", "tvBroadcasts": [{"id": 27, "market": "H", "countryCode": "US", "network": "MSG", "sequenceNumber": 417}, {"id": 28, "market": "A", "countryCode": "US", "network": "MSG-B", "sequenceNumber": 392}], "awayTeam": {"id": 7, "commonName": {"default": "Sabres"}, "placeName": {"default": "Buffalo"}, "placeNameWithPreposition": {"default": "Buffalo", "fr": "de Buffalo"}, "abbrev": "BUF", "logo": "https://assets.nhle.com/logos/nhl/svg/BUF_light.svg", "darkLogo": "https://assets.nhle.com/logos/nhl/svg/BUF_dark.svg", "awaySplitSquad": false, "score": 5}, "homeTeam": {"id": 3, "commonName": {"default": "Rangers"}, "placeName": {"default": "New York"}, "placeNameWithPreposition": {"default": "New York", "fr": "de New York"}, "abbrev": "NYR", "logo": "https://assets.nhle.com/logos/nhl/svg/NYR_light.svg", "darkLogo": "https://assets.nhle.com/logos/nhl/svg/NYR_dark.svg", "homeSplitSquad": false, "score": 2}, "periodDescriptor": {"number": 3, "periodType": "REG", "maxRegulationPeriods": 3}, "gameOutcome": {"lastPeriodType": "REG"}, "winningGoalie": {"playerId": 8481551, "firstInitial": {"default": "C."}, "lastName": {"default": "Ellis"}}, "winningGoalScorer": {"playerId": 8475722, "firstInitial": {"default": "J."}, "lastName": {"default": "Zucker"}}, "threeMinRecap": "/video/buf-at-nyr-recap-6387450084112", "threeMinRecapFr": "/fr/video/buf-vs-nyr-08-01-2026-resume-6387449981112", "condensedGame": "/video/buf-at-nyr-condensed-game-6387448424112", "condensedGameFr": "/fr/video/match-condense-sabres-rangers-08-01-2026-6387449317112", "gameCenterLink": "/gamecenter/buf-vs-nyr/2026/01/08/2025020685"}, {"id": 2025020697, "season": 20252026, "gameType": 2, "gameDate": "2026-01-10", "venue": {"default": "TD Garden"}, "neutralSite": false, "startTimeUTC": "2026-01-10T18:00:00Z", "easternUTCOffset": "-05:00", "venueUTCOffset": "-05:00", "venueTimezone": "US/Eastern", "gameState": "OFF", "gameScheduleState": "OK", "tvBroadcasts": [{"id": 384, "market": "N", "countryCode": "US", "network": "ABC", "sequenceNumber": 1}, {"id": 282, "market": "N", "countryCode": "CA", "network": "SN", "sequenceNumber": 21}], "awayTeam": {"id": 3, "commonName": {"default": "Rangers"}, "placeName": {"default": "New York"}, "placeNameWithPreposition": {"default": "New York", "fr": "de New York"}, "abbrev": "NYR", "logo": "https://assets.nhle.com/logos/nhl/svg/NYR_light.svg", "darkLogo": "https://assets.nhle.com/logos/nhl/svg/NYR_dark.svg", "awaySplitSquad": false, "score": 2}, "homeTeam": {"id": 6, "commonName": {"default": "Bruins"}, "placeName": {"default": "Boston"}, "placeNameWithPreposition": {"default": "Boston", "fr": "de Boston"}, "abbrev": "BOS", "logo": "https://assets.nhle.com/logos/nhl/svg/BOS_light.svg?season=20252026", "darkLogo": "https://assets.nhle.com/logos/nhl/svg/BOS_dark.svg?season=20252026", "homeSplitSquad": false, "score": 10}, "periodDescriptor": {"number": 3, "periodType": "REG", "maxRegulationPeriods": 3}, "gameOutcome": {"lastPeriodType": "REG"}, "winningGoalie": {"playerId": 8480280, "firstInitial": {"default": "J."}, "lastName": {"default": "Swayman"}}, "winningGoalScorer": {"playerId": 8478401, "firstInitial": {"default": "P."}, "lastName": {"default": "Zacha"}}, "threeMinRecap": "/video/nyr-at-bos-recap-6387536580112", "threeMinRecapFr": "/fr/video/nyr-vs-bos-10-01-2026-resume-6387537366112", "condensedGame": "/video/nyr-at-bos-condensed-game-6387536685112", "condensedGameFr": "/fr/video/match-condense-rangers-bruins-10-01-2026-6387536194112", "gameCenterLink": "/gamecenter/nyr-vs-bos/2026/01/10/2025020697"}, {"id": 2025020718, "season": 20252026, "gameType": 2, "gameDate": "2026-01-12", "venue": {"default": "Madison Square Garden"}, "neutralSite": false, "startTimeUTC": "2026-01-13T00:00:00Z", "easternUTCOffset": "-05:00", "venueUTCOffset": "-05:00", "venueTimezone": "America/New_York", "gameState": "OFF", "gameScheduleState": "OK", "tvBroadcasts": [{"id": 324, "market": "N", "countryCode": "US", "network": "NHLN", "sequenceNumber": 35}, {"id": 27, "market": "H", "countryCode": "US", "network": "MSG", "sequenceNumber": 417}, {"id": 554, "market": "A", "countryCode": "US", "network": "KHN/Prime", "sequenceNumber": 348}, {"id": 388, "market": "A", "countryCode": "US", "network": "KONG", "sequenceNumber": 654}], "awayTeam": {"id": 55, "commonName": {"default": "Kraken"}, "placeName": {"default": "Seattle"}, "placeNameWithPreposition": {"default": "Seattle", "fr": "de Seattle"}, "abbrev": "SEA", "logo": "https://assets.nhle.com/logos/nhl/svg/SEA_light.svg", "darkLogo": "https://assets.nhle.com/logos/nhl/svg/SEA_dark.svg", "awaySplitSquad": false, "score": 4}, "homeTeam": {"id": 3, "commonName": {"default": "Rangers"}, "placeName": {"default": "New York"}, "placeNameWithPreposition": {"default": "New York", "fr": "de New York"}, "abbrev": "NYR", "logo": "https://assets.nhle.com/logos/nhl/svg/NYR_light.svg", "darkLogo": "https://assets.nhle.com/logos/nhl/svg/NYR_dark.svg", "homeSplitSquad": false, "score": 2}, "periodDescriptor": {"number": 3, "periodType": "REG", "maxRegulationPeriods": 3}, "gameOutcome": {"lastPeriodType": "REG"}, "winningGoalie": {"playerId": 8475831, "firstInitial": {"default": "P."}, "lastName": {"default": "Grubauer"}}, "winningGoalScorer": {"playerId": 8484800, "firstInitial": {"default": "B."}, "lastName": {"default": "Catton"}}, "threeMinRecap": "/video/sea-at-nyr-recap-6387635329112", "threeMinRecapFr": "/fr/video/sea-vs-nyr-12-01-2026-resume-6387633387112", "condensedGame": "/video/sea-at-nyr-condensed-game-6387635423112", "condensedGameFr": "/fr/video/match-condense-kraken-rangers-12-01-2026-6387634056112", "gameCenterLink": "/gamecenter/sea-vs-nyr/2026/01/12/2025020718"}, {"id": 2025020737, "season": 20252026, "gameType": 2, "gameDate": "2026-01-14", "venue": {"default": "Madison Square Garden"}, "neutralSite": false, "startTimeUTC": "2026-01-15T00:30:00Z", "easternUTCOffset": "-05:00", "venueUTCOffset": "-05:00", "venueTimezone": "America/New_York", "gameState": "OFF", "gameScheduleState": "OK", "tvBroadcasts": [{"id": 282, "market": "N", "countryCode": "CA", "network": "SN", "sequenceNumber": 107}, {"id": 27, "market": "H", "countryCode": "US", "network": "MSG", "sequenceNumber": 417}, {"id": 230, "market": "A", "countryCode": "CA", "network": "RDS2", "sequenceNumber": 144}], "awayTeam": {"id": 9, "commonName": {"default": "Senators", "fr": "S\u00e9nateurs"}, "placeName": {"default": "Ottawa"}, "placeNameWithPreposition": {"default": "Ottawa", "fr": "d'Ottawa"}, "abbrev": "OTT", "logo": "https://assets.nhle.com/logos/nhl/svg/OTT_light.svg", "darkLogo": "https://assets.nhle.com/logos/nhl/svg/OTT_dark.svg", "awaySplitSquad": false, "score": 8}, "homeTeam": {"id": 3, "commonName": {"default": "Rangers"}, "placeName": {"default": "New York"}, "placeNameWithPreposition": {"default": "New York", "fr": "de New York"}, "abbrev": "NYR", "logo": "https://assets.nhle.com/logos/nhl/svg/NYR_light.svg", "darkLogo": "https://assets.nhle.com/logos/nhl/svg/NYR_dark.svg", "homeSplitSquad": false, "score": 4}, "periodDescriptor": {"number": 3, "periodType": "REG", "maxRegulationPeriods": 3}, "gameOutcome": {"lastPeriodType": "REG"}, "winningGoalie": {"playerId": 8482447, "firstInitial": {"default": "L."}, "lastName": {"default": "Meril\u00e4inen"}}, "winningGoalScorer": {"playerId": 8482105, "firstInitial": {"default": "J."}, "lastName": {"default": "Sanderson"}}, "threeMinRecap": "/video/ott-at-nyr-recap-6387740321112", "threeMinRecapFr": "/fr/video/ott-vs-nyr-14-01-2026-resume-6387741022112", "condensedGame": "/video/ott-at-nyr-condensed-game-6387741203112", "condensedGameFr": "/fr/video/match-condense-senators-rangers-14-01-2026-6387739538112", "gameCenterLink": "/gamecenter/ott-vs-nyr/2026/01/14/2025020737"}]}